{"cloud_package_completed_time":"","draft_cloud_capcut_purchase_info":"","draft_cloud_last_action_download":false,"draft_cloud_materials":[],"draft_cloud_purchase_info":"","draft_cloud_template_id":"","draft_cloud_tutorial_info":"","draft_cloud_videocut_purchase_info":"","draft_cover":"draft_cover.jpg","draft_deeplink_url":"","draft_enterprise_info":{"draft_enterprise_extra":"","draft_enterprise_id":"","draft_enterprise_name":"","enterprise_material":[]},"draft_fold_path":"C:/Users/Computer/AppData/Local/CapCut/User Data/Projects/com.lveditor.draft/0920 (1)","draft_id":"33957A39-F0D0-49d3-B8BB-A484EEB9608A","draft_is_ai_packaging_used":false,"draft_is_ai_shorts":false,"draft_is_ai_translate":false,"draft_is_article_video_draft":false,"draft_is_from_deeplink":"false","draft_is_invisible":false,"draft_materials":[{"type":0,"value":[{"create_time":1758413721,"duration":5000000,"extra_info":"001_20250920_2011_Bright Smile Mystery_storyboard_01k5mssb4kfxnrwhn87ga9v9j8.mp4","file_Path":"./Resources/local/a266e6014fc38133dad31ad591397e58.mp4","height":720,"id":"71841899-6b44-4a2d-9ff3-c16ad6c214e5","import_time":1758413863,"import_time_ms":1758413849193302,"item_source":1,"md5":"","metetype":"video","roughcut_time_range":{"duration":5000000,"start":0},"sub_time_range":{"duration":-1,"start":-1},"type":0,"width":1280},{"create_time":1758413732,"duration":5000000,"extra_info":"002_20250920_2011_Bright Smile Mystery_storyboard_01k5mssb5ber6tmsyrm97w3fsh.mp4","file_Path":"./Resources/local/03ee8d028fe887833e30db9ce4b14891.mp4","height":720,"id":"9811be24-28e0-4e11-875e-f0bd9d47f924","import_time":1758413864,"import_time_ms":1758413849205877,"item_source":1,"md5":"","metetype":"video","roughcut_time_range":{"duration":5000000,"start":0},"sub_time_range":{"duration":-1,"start":-1},"type":0,"width":1280},{"create_time":1758413763,"duration":5000000,"extra_info":"003_20250920_2013_No Prompt Available_storyboard_01k5mswsmyf6zajwbg6gsv81t8.mp4","file_Path":"./Resources/local/1dc5e3b3b1664f3838c9c203ff81abb4.mp4","height":720,"id":"86cf4d1a-e984-472c-b48d-d768616df89c","import_time":1758413865,"import_time_ms":1758413849226439,"item_source":1,"md5":"","metetype":"video","roughcut_time_range":{"duration":5000000,"start":0},"sub_time_range":{"duration":-1,"start":-1},"type":0,"width":1280},{"create_time":1758413749,"duration":5000000,"extra_info":"004_20250920_2013_No Prompt Available_storyboard_01k5mswtm1fsqa781se2wykaa2.mp4","file_Path":"./Resources/local/350c121c6887860267bed557fd76bd56.mp4","height":720,"id":"b8d3897f-4397-4deb-9b64-658d3c178338","import_time":1758413866,"import_time_ms":1758413849245728,"item_source":1,"md5":"","metetype":"video","roughcut_time_range":{"duration":5000000,"start":0},"sub_time_range":{"duration":-1,"start":-1},"type":0,"width":1280},{"create_time":1758413781,"duration":5000000,"extra_info":"005_20250920_2014_Nature's Tranquil Beauty_storyboard_01k5msz7phe4ds9x35m784hds4.mp4","file_Path":"./Resources/local/5b8b0f06388c6f2266621042c050d484.mp4","height":720,"id":"09ac3fc5-c004-4657-9b5d-1e9411ced340","import_time":1758413867,"import_time_ms":1758413849261548,"item_source":1,"md5":"","metetype":"video","roughcut_time_range":{"duration":5000000,"start":0},"sub_time_range":{"duration":-1,"start":-1},"type":0,"width":1280},{"create_time":1758413775,"duration":5000000,"extra_info":"006_20250920_2015_Nature's Tranquil Beauty_storyboard_01k5msz7q5exy9pp30vc87f711.mp4","file_Path":"./Resources/local/1eadf56fcc3e338fe4c55205ea26f5a5.mp4","height":720,"id":"c4e8f626-eeb9-4b04-947c-385e6da1b3ce","import_time":1758413868,"import_time_ms":1758413849279171,"item_source":1,"md5":"","metetype":"video","roughcut_time_range":{"duration":5000000,"start":0},"sub_time_range":{"duration":-1,"start":-1},"type":0,"width":1280},{"create_time":1758413790,"duration":5000000,"extra_info":"007_20250920_2015_No Prompt Provided_storyboard_01k5mt10hqebmvv6d3rdvvvpe9.mp4","file_Path":"./Resources/local/f385cf10fe44f8f2cdc390c4d1780f24.mp4","height":720,"id":"c265b590-2f27-4f32-8301-81c687d2b7d2","import_time":1758413869,"import_time_ms":1758413849294500,"item_source":1,"md5":"","metetype":"video","roughcut_time_range":{"duration":5000000,"start":0},"sub_time_range":{"duration":-1,"start":-1},"type":0,"width":1280},{"create_time":1758413798,"duration":5000000,"extra_info":"008_20250920_2016_No Prompt Provided_storyboard_01k5mt0xkeeasvm0ehnvmcd20m.mp4","file_Path":"./Resources/local/c685aed8d7ff755e778bcd64501b8ac9.mp4","height":720,"id":"600c8b68-cc49-46e8-a2eb-43f68af17806","import_time":1758413870,"import_time_ms":1758413849310618,"item_source":1,"md5":"","metetype":"video","roughcut_time_range":{"duration":5000000,"start":0},"sub_time_range":{"duration":-1,"start":-1},"type":0,"width":1280},{"create_time":1758414275,"duration":5000000,"extra_info":"009_20250920_2015_No Prompt Provided_storyboard_01k5mt10hqebmvv6d3rdvvvpe9.mp4","file_Path":"./Resources/local/f3f3a565d47844cee0ca666b4d9712f3.mp4","height":720,"id":"adc2f176-2127-4767-9ced-c9bcbad9c061","import_time":1758414318,"import_time_ms":1758414296029342,"item_source":1,"md5":"","metetype":"video","roughcut_time_range":{"duration":5000000,"start":0},"sub_time_range":{"duration":-1,"start":-1},"type":0,"width":1280},{"create_time":1758454480,"duration":5000000,"extra_info":"011_20250921_0733_Unknown Scene Imagery_storyboard_01k5p0swece3jawsbzc5mjsw9s.mp4","file_Path":"./Resources/local/fb3a703a355dfd2fb6976cebedc0250a.mp4","height":720,"id":"d9a66404-7955-4136-989a-ae9e2410b4ce","import_time":1758454523,"import_time_ms":1758454500070845,"item_source":1,"md5":"","metetype":"video","roughcut_time_range":{"duration":5000000,"start":0},"sub_time_range":{"duration":-1,"start":-1},"type":0,"width":1280},{"create_time":1758454561,"duration":5000000,"extra_info":"012_20250921_0734_Awaiting Scene Description_storyboard_01k5p0w859fe79ws9f6yg3p1wz.mp4","file_Path":"./Resources/local/6e1761bdf26f80faa78a19eec82c0aee.mp4","height":720,"id":"8184d3f6-3f77-4fde-bc46-289f210cce46","import_time":1758454595,"import_time_ms":1758454571479912,"item_source":1,"md5":"","metetype":"video","roughcut_time_range":{"duration":5000000,"start":0},"sub_time_range":{"duration":-1,"start":-1},"type":0,"width":1280},{"create_time":1758454683,"duration":5000000,"extra_info":"013_20250921_0736_Missing Scene Description_storyboard_01k5p0z4zren1rmcc8chb7tyg7.mp4","file_Path":"./Resources/local/e118483f5c381cf0c96890f01f7b1ec6.mp4","height":720,"id":"d6ec584b-65fe-4922-969d-c0834b42c12d","import_time":1758454727,"import_time_ms":1758454702249877,"item_source":1,"md5":"","metetype":"video","roughcut_time_range":{"duration":5000000,"start":0},"sub_time_range":{"duration":-1,"start":-1},"type":0,"width":1280},{"create_time":1758454735,"duration":5000000,"extra_info":"014_20250921_0737_Abstract Imagery Exploration_storyboard_01k5p11ddhe2fsa48cj2n7sqgf.mp4","file_Path":"./Resources/local/5a96c487c016ad3925bd1c7ddb27dd1d.mp4","height":720,"id":"9aecbce0-a8fd-4fe7-816f-2391d7e9e1d4","import_time":1758454769,"import_time_ms":1758454743458842,"item_source":1,"md5":"","metetype":"video","roughcut_time_range":{"duration":5000000,"start":0},"sub_time_range":{"duration":-1,"start":-1},"type":0,"width":1280},{"create_time":1758454825,"duration":5000000,"extra_info":"015_20250921_0739_Nature's Serenity_storyboard_01k5p15390e3ab0vsdtvwr7smv.mp4","file_Path":"./Resources/local/6a7e715b42baa2c0c28e76f090075c8e.mp4","height":720,"id":"3e63f976-41a0-4440-8e51-ec69f13ac1c1","import_time":1758454916,"import_time_ms":1758454888258768,"item_source":1,"md5":"","metetype":"video","roughcut_time_range":{"duration":5000000,"start":0},"sub_time_range":{"duration":-1,"start":-1},"type":0,"width":1280},{"create_time":1758454840,"duration":5000000,"extra_info":"016_20250921_0739_Nature's Serenity_storyboard_01k5p15398fgyvcesqsyckt987.mp4","file_Path":"./Resources/local/9f582b2eb8de0c798d8682ca86555412.mp4","height":720,"id":"f6b80f05-4aa6-421a-bbd5-27b592988047","import_time":1758454931,"import_time_ms":1758454902767763,"item_source":1,"md5":"","metetype":"video","roughcut_time_range":{"duration":5000000,"start":0},"sub_time_range":{"duration":-1,"start":-1},"type":0,"width":1280},{"create_time":1758455159,"duration":5000000,"extra_info":"017_20250921_0744_Awaiting User Prompt_storyboard_01k5p1edw4e4r87dckrdm44v5w.mp4","file_Path":"./Resources/local/6ae456651ba61a35d42d8afc3c416ebf.mp4","height":720,"id":"2c55a5fe-1842-4432-9dc8-ae358918ec9e","import_time":1758455225,"import_time_ms":1758455193405880,"item_source":1,"md5":"","metetype":"video","roughcut_time_range":{"duration":5000000,"start":0},"sub_time_range":{"duration":-1,"start":-1},"type":0,"width":1280},{"create_time":1758455245,"duration":5000000,"extra_info":"018_20250921_0746_Title Pending_storyboard_01k5p1j0gbeq6v0gdhhqt34j4n.mp4","file_Path":"./Resources/local/1d4e22c285e6931b92a01c933b6a0aba.mp4","height":720,"id":"bc9db98b-4bb2-4935-9c8f-c051663cbaf0","import_time":1758455288,"import_time_ms":1758455255576982,"item_source":1,"md5":"","metetype":"video","roughcut_time_range":{"duration":5000000,"start":0},"sub_time_range":{"duration":-1,"start":-1},"type":0,"width":1280},{"create_time":1758455338,"duration":5000000,"extra_info":"019_20250921_0747_Imagery Captured Moments_storyboard_01k5p1m5g5f0j9rx2b5r58f812.mp4","file_Path":"./Resources/local/79b27e9fc84254a2df1c9b4bbd620017.mp4","height":720,"id":"949e29c7-bc25-4692-894e-e9e656b41062","import_time":1758455392,"import_time_ms":1758455357643838,"item_source":1,"md5":"","metetype":"video","roughcut_time_range":{"duration":5000000,"start":0},"sub_time_range":{"duration":-1,"start":-1},"type":0,"width":1280},{"create_time":1758455423,"duration":5000000,"extra_info":"020_20250921_0749_Beautiful Image Collection_storyboard_01k5p1pxtwf40scfb0s1kahr1d.mp4","file_Path":"./Resources/local/87f3fc49527ea26fa18e1dfc785332a4.mp4","height":720,"id":"f2d87c86-fb37-4665-8d27-ec91ef11fdce","import_time":1758455468,"import_time_ms":1758455432646893,"item_source":1,"md5":"","metetype":"video","roughcut_time_range":{"duration":5000000,"start":0},"sub_time_range":{"duration":-1,"start":-1},"type":0,"width":1280}]},{"type":1,"value":[]},{"type":2,"value":[]},{"type":3,"value":[{"create_time":0,"duration":0,"extra_info":"{\n  \"src\": \"C:/Users/Computer/AppData/Local/CapCut/User Data/Projects/com.lveditor.draft/0920 (1)/Resources/local/a266e6014fc38133dad31ad591397e58.mp4\"\n}","file_Path":"./55d008e099061181477908781a11d37f.mp4","height":0,"id":"AD321A6E-B799-4cf3-9EED-9EB4AA48DFD0","import_time":1758414097,"import_time_ms":-1,"item_source":1,"md5":"","metetype":"none","roughcut_time_range":{"duration":-1,"start":-1},"sub_time_range":{"duration":-1,"start":-1},"type":3,"width":0},{"create_time":0,"duration":0,"extra_info":"{\n  \"src\": \"C:/Users/Computer/AppData/Local/CapCut/User Data/Projects/com.lveditor.draft/0920 (1)/Resources/local/1dc5e3b3b1664f3838c9c203ff81abb4.mp4\"\n}","file_Path":"./a247276a991c45e0fdf48774c7fbcba5.mp4","height":0,"id":"9C1963F1-DBF8-402d-A1BF-C9F5106F527B","import_time":1758414137,"import_time_ms":-1,"item_source":1,"md5":"","metetype":"none","roughcut_time_range":{"duration":-1,"start":-1},"sub_time_range":{"duration":-1,"start":-1},"type":3,"width":0},{"create_time":0,"duration":0,"extra_info":"{\n  \"src\": \"C:/Users/Computer/AppData/Local/CapCut/User Data/Projects/com.lveditor.draft/0920 (1)/Resources/local/5b8b0f06388c6f2266621042c050d484.mp4\"\n}","file_Path":"./1ba8a1f6b6fc93d55ae474fe6a655ccb.mp4","height":0,"id":"C3A2AFC6-290E-4346-B640-92793791FDD7","import_time":1758414203,"import_time_ms":-1,"item_source":1,"md5":"","metetype":"none","roughcut_time_range":{"duration":-1,"start":-1},"sub_time_range":{"duration":-1,"start":-1},"type":3,"width":0},{"create_time":0,"duration":0,"extra_info":"{\n  \"src\": \"C:/Users/Computer/AppData/Local/CapCut/User Data/Projects/com.lveditor.draft/0920 (1)/Resources/local/350c121c6887860267bed557fd76bd56.mp4\"\n}","file_Path":"./f9b8c8fa8e77c1dcb722cd278a26879b.mp4","height":0,"id":"1531FA38-AA4D-4222-8A1F-0CBAC9140ED1","import_time":1758414265,"import_time_ms":-1,"item_source":1,"md5":"","metetype":"none","roughcut_time_range":{"duration":-1,"start":-1},"sub_time_range":{"duration":-1,"start":-1},"type":3,"width":0},{"create_time":0,"duration":0,"extra_info":"{\n  \"src\": \"C:/Users/Computer/AppData/Local/CapCut/User Data/Projects/com.lveditor.draft/0920 (1)/Resources/local/f3f3a565d47844cee0ca666b4d9712f3.mp4\"\n}","file_Path":"./0bf2e52a3054129c0746cca92480650c.mp4","height":0,"id":"04CDDEF9-4F4B-4237-A9DB-4585A15745C8","import_time":1758414330,"import_time_ms":-1,"item_source":1,"md5":"","metetype":"none","roughcut_time_range":{"duration":-1,"start":-1},"sub_time_range":{"duration":-1,"start":-1},"type":3,"width":0},{"create_time":0,"duration":0,"extra_info":"{\n  \"src\": \"C:/Users/Computer/AppData/Local/CapCut/User Data/Projects/com.lveditor.draft/0920 (1)/Resources/local/c685aed8d7ff755e778bcd64501b8ac9.mp4\"\n}","file_Path":"./07425fc6ee45eb4185d3e39aec3e3608.mp4","height":0,"id":"AF7E3FDE-D3DF-4564-9CC3-0A4BF4C08002","import_time":1758414343,"import_time_ms":-1,"item_source":1,"md5":"","metetype":"none","roughcut_time_range":{"duration":-1,"start":-1},"sub_time_range":{"duration":-1,"start":-1},"type":3,"width":0},{"create_time":0,"duration":0,"extra_info":"{\n  \"src\": \"C:/Users/Computer/AppData/Local/CapCut/User Data/Projects/com.lveditor.draft/0920 (1)/Resources/local/6a7e715b42baa2c0c28e76f090075c8e.mp4\"\n}","file_Path":"./3bd32dcf20c5b05b85b77609c024561f.mp4","height":0,"id":"149503F5-9C32-4c94-8737-2D7519241AFD","import_time":1758454913,"import_time_ms":-1,"item_source":1,"md5":"","metetype":"none","roughcut_time_range":{"duration":-1,"start":-1},"sub_time_range":{"duration":-1,"start":-1},"type":3,"width":0},{"create_time":0,"duration":0,"extra_info":"{\n  \"src\": \"C:/Users/Computer/AppData/Local/CapCut/User Data/Projects/com.lveditor.draft/0920 (1)/Resources/local/9f582b2eb8de0c798d8682ca86555412.mp4\"\n}","file_Path":"./b85828c03327677a0c67c36e79675f73.mp4","height":0,"id":"517EC272-AEE1-49f4-9A9F-B6CE089806B5","import_time":1758454950,"import_time_ms":-1,"item_source":1,"md5":"","metetype":"none","roughcut_time_range":{"duration":-1,"start":-1},"sub_time_range":{"duration":-1,"start":-1},"type":3,"width":0}]},{"type":6,"value":[]},{"type":7,"value":[]}],"draft_materials_copied_info":[{"dst_path":"Resources/local/fb3a703a355dfd2fb6976cebedc0250a.mp4","src_path":"C:/Users/Computer/Downloads/011_20250921_0733_Unknown Scene Imagery_storyboard_01k5p0swece3jawsbzc5mjsw9s.mp4"},{"dst_path":"Resources/local/a266e6014fc38133dad31ad591397e58.mp4","src_path":"C:/Users/Computer/Downloads/001_20250920_2011_Bright Smile Mystery_storyboard_01k5mssb4kfxnrwhn87ga9v9j8.mp4"},{"dst_path":"Resources/local/c685aed8d7ff755e778bcd64501b8ac9.mp4","src_path":"C:/Users/Computer/Downloads/008_20250920_2016_No Prompt Provided_storyboard_01k5mt0xkeeasvm0ehnvmcd20m.mp4"},{"dst_path":"Resources/local/03ee8d028fe887833e30db9ce4b14891.mp4","src_path":"C:/Users/Computer/Downloads/002_20250920_2011_Bright Smile Mystery_storyboard_01k5mssb5ber6tmsyrm97w3fsh.mp4"},{"dst_path":"Resources/local/1dc5e3b3b1664f3838c9c203ff81abb4.mp4","src_path":"C:/Users/Computer/Downloads/003_20250920_2013_No Prompt Available_storyboard_01k5mswsmyf6zajwbg6gsv81t8.mp4"},{"dst_path":"Resources/local/f385cf10fe44f8f2cdc390c4d1780f24.mp4","src_path":"C:/Users/Computer/Downloads/007_20250920_2015_No Prompt Provided_storyboard_01k5mt10hqebmvv6d3rdvvvpe9.mp4"},{"dst_path":"Resources/local/6a7e715b42baa2c0c28e76f090075c8e.mp4","src_path":"C:/Users/Computer/Downloads/015_20250921_0739_Nature's Serenity_storyboard_01k5p15390e3ab0vsdtvwr7smv.mp4"},{"dst_path":"Resources/local/5b8b0f06388c6f2266621042c050d484.mp4","src_path":"C:/Users/Computer/Downloads/005_20250920_2014_Nature's Tranquil Beauty_storyboard_01k5msz7phe4ds9x35m784hds4.mp4"},{"dst_path":"Resources/local/1eadf56fcc3e338fe4c55205ea26f5a5.mp4","src_path":"C:/Users/Computer/Downloads/006_20250920_2015_Nature's Tranquil Beauty_storyboard_01k5msz7q5exy9pp30vc87f711.mp4"},{"dst_path":"Resources/local/9f582b2eb8de0c798d8682ca86555412.mp4","src_path":"C:/Users/Computer/Downloads/016_20250921_0739_Nature's Serenity_storyboard_01k5p15398fgyvcesqsyckt987.mp4"},{"dst_path":"Resources/local/350c121c6887860267bed557fd76bd56.mp4","src_path":"C:/Users/Computer/Downloads/004_20250920_2013_No Prompt Available_storyboard_01k5mswtm1fsqa781se2wykaa2.mp4"},{"dst_path":"Resources/local/930e36a5000785cbc708232156f0cf38.mp4","src_path":"C:/Users/Computer/AppData/Local/CapCut/User Data/Cloud files/001_20250920_2011_Bright Smile Mystery_storyboard_01k5mssb4kfxnrwhn87ga9v9j8.mp4"},{"dst_path":"Resources/local/b77a0cf8d245046d5a99308941438172.mp4","src_path":"C:/Users/Computer/AppData/Local/CapCut/User Data/Cloud files/002_20250920_2011_Bright Smile Mystery_storyboard_01k5mssb5ber6tmsyrm97w3fsh.mp4"},{"dst_path":"Resources/local/04d529574550670fb831e60b3d3547ab.mp4","src_path":"C:/Users/Computer/AppData/Local/CapCut/User Data/Cloud files/003_20250920_2013_No Prompt Available_storyboard_01k5mswsmyf6zajwbg6gsv81t8.mp4"},{"dst_path":"Resources/local/79b27e9fc84254a2df1c9b4bbd620017.mp4","src_path":"C:/Users/Computer/Downloads/019_20250921_0747_Imagery Captured Moments_storyboard_01k5p1m5g5f0j9rx2b5r58f812.mp4"},{"dst_path":"Resources/local/4455a4521d3b23196f51c3957a8af0f9.mp4","src_path":"C:/Users/Computer/AppData/Local/CapCut/User Data/Cloud files/016_20250921_0739_Nature's Serenity_storyboard_01k5p15398fgyvcesqsyckt987.mp4"},{"dst_path":"Resources/local/3d2a67f5851518aa7448700e179c384a.mp4","src_path":"C:/Users/Computer/AppData/Local/CapCut/User Data/Cloud files/004_20250920_2013_No Prompt Available_storyboard_01k5mswtm1fsqa781se2wykaa2.mp4"},{"dst_path":"Resources/local/00f02290e906b3442813a71341dedc13.mp4","src_path":"C:/Users/Computer/AppData/Local/CapCut/User Data/Cloud files/005_20250920_2014_Nature's Tranquil Beauty_storyboard_01k5msz7phe4ds9x35m784hds4.mp4"},{"dst_path":"Resources/local/f3f3a565d47844cee0ca666b4d9712f3.mp4","src_path":"C:/Users/Computer/Downloads/009_20250920_2015_No Prompt Provided_storyboard_01k5mt10hqebmvv6d3rdvvvpe9.mp4"},{"dst_path":"Resources/local/dbcaa805078ba5998a3063bf33873872.mp4","src_path":"C:/Users/Computer/AppData/Local/CapCut/User Data/Cloud files/009_20250920_2015_No Prompt Provided_storyboard_01k5mt10hqebmvv6d3rdvvvpe9.mp4"},{"dst_path":"Resources/local/87f3fc49527ea26fa18e1dfc785332a4.mp4","src_path":"C:/Users/Computer/Downloads/020_20250921_0749_Beautiful Image Collection_storyboard_01k5p1pxtwf40scfb0s1kahr1d.mp4"},{"dst_path":"Resources/local/2bde93096ed797ae5793ca43a6d3f3fc.mp4","src_path":"C:/Users/Computer/AppData/Local/CapCut/User Data/Cloud files/014_20250921_0737_Abstract Imagery Exploration_storyboard_01k5p11ddhe2fsa48cj2n7sqgf.mp4"},{"dst_path":"Resources/local/44cac47fb9080bfc89df007f7280a192.mp4","src_path":"C:/Users/Computer/AppData/Local/CapCut/User Data/Cloud files/008_20250920_2016_No Prompt Provided_storyboard_01k5mt0xkeeasvm0ehnvmcd20m.mp4"},{"dst_path":"Resources/local/5a96c487c016ad3925bd1c7ddb27dd1d.mp4","src_path":"C:/Users/Computer/Downloads/014_20250921_0737_Abstract Imagery Exploration_storyboard_01k5p11ddhe2fsa48cj2n7sqgf.mp4"},{"dst_path":"Resources/local/0814608256200604fcf15083079ef1e3.mp4","src_path":"C:/Users/Computer/AppData/Local/CapCut/User Data/Cloud files/011_20250921_0733_Unknown Scene Imagery_storyboard_01k5p0swece3jawsbzc5mjsw9s.mp4"},{"dst_path":"Resources/local/13dfb658befdad39293bf1a7f36bd8c8.mp4","src_path":"C:/Users/Computer/AppData/Local/CapCut/User Data/Cloud files/020_20250921_0749_Beautiful Image Collection_storyboard_01k5p1pxtwf40scfb0s1kahr1d.mp4"},{"dst_path":"Resources/local/d554e6385fe9999bf31d77e3d20dc97c.mp4","src_path":"C:/Users/Computer/AppData/Local/CapCut/User Data/Cloud files/012_20250921_0734_Awaiting Scene Description_storyboard_01k5p0w859fe79ws9f6yg3p1wz.mp4"},{"dst_path":"Resources/local/e118483f5c381cf0c96890f01f7b1ec6.mp4","src_path":"C:/Users/Computer/Downloads/013_20250921_0736_Missing Scene Description_storyboard_01k5p0z4zren1rmcc8chb7tyg7.mp4"},{"dst_path":"Resources/local/6d06d289752ab8ae7f7dc812e88c0bc2.mp4","src_path":"C:/Users/Computer/AppData/Local/CapCut/User Data/Cloud files/013_20250921_0736_Missing Scene Description_storyboard_01k5p0z4zren1rmcc8chb7tyg7.mp4"},{"dst_path":"Resources/local/94b95d472e993fcf6a495e62c48db9f3.mp4","src_path":"C:/Users/Computer/AppData/Local/CapCut/User Data/Cloud files/6a7e715b42baa2c0c28e76f090075c8e.mp4"},{"dst_path":"Resources/local/67aee1b4a5a2bb104793d7680abf0784.mp4","src_path":"C:/Users/Computer/AppData/Local/CapCut/User Data/Cloud files/015_20250921_0739_Nature's Serenity_storyboard_01k5p15390e3ab0vsdtvwr7smv.mp4"},{"dst_path":"Resources/local/6ae456651ba61a35d42d8afc3c416ebf.mp4","src_path":"C:/Users/Computer/Downloads/017_20250921_0744_Awaiting User Prompt_storyboard_01k5p1edw4e4r87dckrdm44v5w.mp4"},{"dst_path":"Resources/local/de14334ec535be652a1b30220da5e6ce.mp4","src_path":"C:/Users/Computer/AppData/Local/CapCut/User Data/Cloud files/017_20250921_0744_Awaiting User Prompt_storyboard_01k5p1edw4e4r87dckrdm44v5w.mp4"},{"dst_path":"Resources/local/1d4e22c285e6931b92a01c933b6a0aba.mp4","src_path":"C:/Users/Computer/Downloads/018_20250921_0746_Title Pending_storyboard_01k5p1j0gbeq6v0gdhhqt34j4n.mp4"},{"dst_path":"Resources/local/310fa73d0f4cda0a37c13795380e72ef.mp4","src_path":"C:/Users/Computer/AppData/Local/CapCut/User Data/Cloud files/018_20250921_0746_Title Pending_storyboard_01k5p1j0gbeq6v0gdhhqt34j4n.mp4"},{"dst_path":"Resources/local/6bb938b09a595a940a013e0a7d3ad5c9.mp4","src_path":"C:/Users/Computer/AppData/Local/CapCut/User Data/Cloud files/79b27e9fc84254a2df1c9b4bbd620017.mp4"},{"dst_path":"Resources/local/ed75422a7cf70fadb9d05d46b99547b1.mp4","src_path":"C:/Users/Computer/AppData/Local/CapCut/User Data/Cloud files/019_20250921_0747_Imagery Captured Moments_storyboard_01k5p1m5g5f0j9rx2b5r58f812.mp4"}],"draft_name":"0920 (1)","draft_new_version":"","draft_removable_storage_device":"","draft_root_path":"C:\\Users\\Computer\\AppData\\Local\\CapCut\\User Data\\Projects\\com.lveditor.draft","draft_segment_extra_info":[],"draft_timeline_materials_size_":2647,"draft_type":"","tm_draft_cloud_completed":"","tm_draft_cloud_modified":0,"tm_draft_create":1758413587072486,"tm_draft_modified":1758455546875591,"tm_draft_removed":0,"tm_duration":102000000}